fastdb/__init__.py
fastdb/common/__init__.py
fastdb/firestore/__init__.py
fastdb-1.0.1.dist-info/LICENSE
fastdb-1.0.1.dist-info/WHEEL
fastdb-1.0.1.dist-info/METADATA
fastdb-1.0.1.dist-info/RECORD
