Metadata-Version: 2.1
Name: fastdb
Version: 1.0.1
Summary: Faster database operations using Python
Author-email: Sarmad Gulzar <sarmadgulzar@hotmail.com>
Classifier: License :: OSI Approved :: MIT License
Project-URL: Home, https://github.com/sarmadgulzar/fastdb
